dictmatching/__init__.py
dictmatching/_dis.py
dictmatching/dictmatching.py
dictmatching-0.1.1.dist-info/LICENSE.txt
dictmatching-0.1.1.dist-info/METADATA
dictmatching-0.1.1.dist-info/RECORD
dictmatching-0.1.1.dist-info/WHEEL
dictmatching-0.1.1.dist-info/top_level.txt
